[{"label": "class", "confidence": 0.8435366153717041, "topleft": {"x": 126, "y": 1}, "bottomright": {"x": 137, "y": 14}}, {"label": "class", "confidence": 0.7561026811599731, "topleft": {"x": 139, "y": 2}, "bottomright": {"x": 149, "y": 12}}, {"label": "class", "confidence": 0.6767213344573975, "topleft": {"x": 21, "y": 6}, "bottomright": {"x": 33, "y": 19}}, {"label": "class", "confidence": 0.6959531307220459, "topleft": {"x": 149, "y": 12}, "bottomright": {"x": 160, "y": 24}}, {"label": "class", "confidence": 0.3987509608268738, "topleft": {"x": 161, "y": 7}, "bottomright": {"x": 172, "y": 20}}, {"label": "class", "confidence": 0.6314042806625366, "topleft": {"x": 170, "y": 6}, "bottomright": {"x": 181, "y": 19}}, {"label": "class", "confidence": 0.7832261323928833, "topleft": {"x": 4, "y": 18}, "bottomright": {"x": 13, "y": 28}}, {"label": "class", "confidence": 0.6828058362007141, "topleft": {"x": 105, "y": 23}, "bottomright": {"x": 116, "y": 35}}, {"label": "class", "confidence": 0.6462891101837158, "topleft": {"x": 135, "y": 23}, "bottomright": {"x": 145, "y": 36}}, {"label": "class", "confidence": 0.8572004437446594, "topleft": {"x": 0, "y": 30}, "bottomright": {"x": 8, "y": 42}}, {"label": "class", "confidence": 0.47992604970932007, "topleft": {"x": 110, "y": 34}, "bottomright": {"x": 123, "y": 46}}, {"label": "class", "confidence": 0.67294842004776, "topleft": {"x": 34, "y": 43}, "bottomright": {"x": 46, "y": 55}}, {"label": "class", "confidence": 0.6380938291549683, "topleft": {"x": 177, "y": 44}, "bottomright": {"x": 186, "y": 55}}, {"label": "class", "confidence": 0.6269005537033081, "topleft": {"x": 25, "y": 59}, "bottomright": {"x": 34, "y": 72}}, {"label": "class", "confidence": 0.5233418345451355, "topleft": {"x": 27, "y": 63}, "bottomright": {"x": 38, "y": 75}}, {"label": "class", "confidence": 0.6635934114456177, "topleft": {"x": 132, "y": 61}, "bottomright": {"x": 143, "y": 75}}, {"label": "class", "confidence": 0.668270468711853, "topleft": {"x": 43, "y": 76}, "bottomright": {"x": 53, "y": 88}}, {"label": "class", "confidence": 0.591376781463623, "topleft": {"x": 98, "y": 72}, "bottomright": {"x": 109, "y": 85}}, {"label": "class", "confidence": 0.4998549818992615, "topleft": {"x": 19, "y": 80}, "bottomright": {"x": 28, "y": 91}}, {"label": "class", "confidence": 0.7412855625152588, "topleft": {"x": 55, "y": 87}, "bottomright": {"x": 65, "y": 99}}, {"label": "class", "confidence": 0.7227588891983032, "topleft": {"x": 90, "y": 80}, "bottomright": {"x": 101, "y": 92}}, {"label": "class", "confidence": 0.7580257058143616, "topleft": {"x": 108, "y": 79}, "bottomright": {"x": 120, "y": 93}}, {"label": "class", "confidence": 0.6892704367637634, "topleft": {"x": 135, "y": 89}, "bottomright": {"x": 146, "y": 102}}, {"label": "class", "confidence": 0.6336867213249207, "topleft": {"x": 88, "y": 101}, "bottomright": {"x": 99, "y": 113}}, {"label": "class", "confidence": 0.5252994894981384, "topleft": {"x": 121, "y": 107}, "bottomright": {"x": 133, "y": 119}}, {"label": "class", "confidence": 0.598373293876648, "topleft": {"x": 161, "y": 107}, "bottomright": {"x": 173, "y": 119}}, {"label": "class", "confidence": 0.42496979236602783, "topleft": {"x": 70, "y": 125}, "bottomright": {"x": 80, "y": 137}}, {"label": "class", "confidence": 0.5860744714736938, "topleft": {"x": 192, "y": 124}, "bottomright": {"x": 199, "y": 136}}, {"label": "class", "confidence": 0.37933871150016785, "topleft": {"x": 78, "y": 136}, "bottomright": {"x": 88, "y": 150}}, {"label": "class", "confidence": 0.5532566905021667, "topleft": {"x": 156, "y": 136}, "bottomright": {"x": 169, "y": 148}}, {"label": "class", "confidence": 0.7922007441520691, "topleft": {"x": 190, "y": 133}, "bottomright": {"x": 199, "y": 145}}, {"label": "class", "confidence": 0.7198454737663269, "topleft": {"x": 179, "y": 150}, "bottomright": {"x": 189, "y": 162}}, {"label": "class", "confidence": 0.3915753662586212, "topleft": {"x": 74, "y": 161}, "bottomright": {"x": 82, "y": 173}}, {"label": "class", "confidence": 0.5286769866943359, "topleft": {"x": 90, "y": 160}, "bottomright": {"x": 100, "y": 172}}, {"label": "class", "confidence": 0.6950646638870239, "topleft": {"x": 166, "y": 163}, "bottomright": {"x": 178, "y": 177}}, {"label": "class", "confidence": 0.6141360998153687, "topleft": {"x": 119, "y": 173}, "bottomright": {"x": 130, "y": 186}}, {"label": "class", "confidence": 0.44223085045814514, "topleft": {"x": 163, "y": 181}, "bottomright": {"x": 172, "y": 194}}]