[{"label": "class", "confidence": 0.8771312236785889, "topleft": {"x": 18, "y": 0}, "bottomright": {"x": 28, "y": 7}}, {"label": "class", "confidence": 0.4803667366504669, "topleft": {"x": 54, "y": 4}, "bottomright": {"x": 66, "y": 14}}, {"label": "class", "confidence": 0.7371262907981873, "topleft": {"x": 124, "y": 0}, "bottomright": {"x": 133, "y": 4}}, {"label": "class", "confidence": 0.6431037187576294, "topleft": {"x": 91, "y": 8}, "bottomright": {"x": 101, "y": 18}}, {"label": "class", "confidence": 0.7421764731407166, "topleft": {"x": 93, "y": 19}, "bottomright": {"x": 105, "y": 34}}, {"label": "class", "confidence": 0.670788049697876, "topleft": {"x": 15, "y": 33}, "bottomright": {"x": 24, "y": 45}}, {"label": "class", "confidence": 0.528367280960083, "topleft": {"x": 17, "y": 28}, "bottomright": {"x": 27, "y": 40}}, {"label": "class", "confidence": 0.662163257598877, "topleft": {"x": 101, "y": 30}, "bottomright": {"x": 110, "y": 43}}, {"label": "class", "confidence": 0.5207262635231018, "topleft": {"x": 145, "y": 32}, "bottomright": {"x": 156, "y": 44}}, {"label": "class", "confidence": 0.5323888659477234, "topleft": {"x": 144, "y": 36}, "bottomright": {"x": 152, "y": 45}}, {"label": "class", "confidence": 0.7387940883636475, "topleft": {"x": 153, "y": 29}, "bottomright": {"x": 164, "y": 40}}, {"label": "class", "confidence": 0.7534692287445068, "topleft": {"x": 190, "y": 27}, "bottomright": {"x": 198, "y": 39}}, {"label": "class", "confidence": 0.6045417189598083, "topleft": {"x": 45, "y": 55}, "bottomright": {"x": 55, "y": 66}}, {"label": "class", "confidence": 0.33378297090530396, "topleft": {"x": 98, "y": 54}, "bottomright": {"x": 107, "y": 68}}, {"label": "class", "confidence": 0.6897780895233154, "topleft": {"x": 121, "y": 53}, "bottomright": {"x": 133, "y": 65}}, {"label": "class", "confidence": 0.5029327869415283, "topleft": {"x": 75, "y": 57}, "bottomright": {"x": 87, "y": 71}}, {"label": "class", "confidence": 0.6454006433486938, "topleft": {"x": 93, "y": 60}, "bottomright": {"x": 103, "y": 72}}, {"label": "class", "confidence": 0.7606089115142822, "topleft": {"x": 191, "y": 77}, "bottomright": {"x": 199, "y": 88}}, {"label": "class", "confidence": 0.6152478456497192, "topleft": {"x": 14, "y": 85}, "bottomright": {"x": 24, "y": 96}}, {"label": "class", "confidence": 0.6522979736328125, "topleft": {"x": 33, "y": 80}, "bottomright": {"x": 43, "y": 92}}, {"label": "class", "confidence": 0.33749091625213623, "topleft": {"x": 162, "y": 86}, "bottomright": {"x": 172, "y": 100}}, {"label": "class", "confidence": 0.6162489056587219, "topleft": {"x": 22, "y": 95}, "bottomright": {"x": 31, "y": 106}}, {"label": "class", "confidence": 0.6618615984916687, "topleft": {"x": 43, "y": 93}, "bottomright": {"x": 53, "y": 104}}, {"label": "class", "confidence": 0.7216758131980896, "topleft": {"x": 176, "y": 93}, "bottomright": {"x": 187, "y": 104}}, {"label": "class", "confidence": 0.5048704147338867, "topleft": {"x": 46, "y": 117}, "bottomright": {"x": 57, "y": 131}}, {"label": "class", "confidence": 0.6340658664703369, "topleft": {"x": 136, "y": 112}, "bottomright": {"x": 146, "y": 124}}, {"label": "class", "confidence": 0.6786215305328369, "topleft": {"x": 178, "y": 111}, "bottomright": {"x": 190, "y": 123}}, {"label": "class", "confidence": 0.5646212100982666, "topleft": {"x": 179, "y": 140}, "bottomright": {"x": 189, "y": 151}}, {"label": "class", "confidence": 0.5658724308013916, "topleft": {"x": 52, "y": 142}, "bottomright": {"x": 63, "y": 154}}, {"label": "class", "confidence": 0.49406343698501587, "topleft": {"x": 144, "y": 147}, "bottomright": {"x": 152, "y": 158}}, {"label": "class", "confidence": 0.8194037079811096, "topleft": {"x": 0, "y": 155}, "bottomright": {"x": 7, "y": 166}}, {"label": "class", "confidence": 0.7366657853126526, "topleft": {"x": 105, "y": 153}, "bottomright": {"x": 117, "y": 166}}, {"label": "class", "confidence": 0.6183323860168457, "topleft": {"x": 186, "y": 160}, "bottomright": {"x": 196, "y": 172}}, {"label": "class", "confidence": 0.6152496933937073, "topleft": {"x": 120, "y": 163}, "bottomright": {"x": 133, "y": 176}}, {"label": "class", "confidence": 0.7230981588363647, "topleft": {"x": 145, "y": 177}, "bottomright": {"x": 155, "y": 188}}, {"label": "class", "confidence": 0.42168036103248596, "topleft": {"x": 160, "y": 178}, "bottomright": {"x": 171, "y": 191}}, {"label": "class", "confidence": 0.3322235345840454, "topleft": {"x": 155, "y": 179}, "bottomright": {"x": 166, "y": 190}}, {"label": "class", "confidence": 0.6487473845481873, "topleft": {"x": 165, "y": 180}, "bottomright": {"x": 174, "y": 191}}, {"label": "class", "confidence": 0.6478980779647827, "topleft": {"x": 63, "y": 191}, "bottomright": {"x": 73, "y": 199}}, {"label": "class", "confidence": 0.4830624759197235, "topleft": {"x": 150, "y": 185}, "bottomright": {"x": 158, "y": 197}}]