[{"label": "class", "confidence": 0.5293485522270203, "topleft": {"x": 25, "y": 23}, "bottomright": {"x": 34, "y": 36}}, {"label": "class", "confidence": 0.5580399036407471, "topleft": {"x": 50, "y": 28}, "bottomright": {"x": 59, "y": 38}}, {"label": "class", "confidence": 0.6274709105491638, "topleft": {"x": 102, "y": 33}, "bottomright": {"x": 113, "y": 45}}, {"label": "class", "confidence": 0.6916776299476624, "topleft": {"x": 30, "y": 41}, "bottomright": {"x": 40, "y": 54}}, {"label": "class", "confidence": 0.6158002018928528, "topleft": {"x": 50, "y": 49}, "bottomright": {"x": 60, "y": 61}}, {"label": "class", "confidence": 0.6561565399169922, "topleft": {"x": 75, "y": 49}, "bottomright": {"x": 87, "y": 64}}, {"label": "class", "confidence": 0.6354929208755493, "topleft": {"x": 63, "y": 66}, "bottomright": {"x": 75, "y": 78}}, {"label": "class", "confidence": 0.6361016631126404, "topleft": {"x": 98, "y": 72}, "bottomright": {"x": 109, "y": 84}}, {"label": "class", "confidence": 0.7446795105934143, "topleft": {"x": 193, "y": 75}, "bottomright": {"x": 199, "y": 87}}, {"label": "class", "confidence": 0.5032716989517212, "topleft": {"x": 13, "y": 85}, "bottomright": {"x": 25, "y": 97}}, {"label": "class", "confidence": 0.3466370105743408, "topleft": {"x": 20, "y": 85}, "bottomright": {"x": 30, "y": 96}}, {"label": "class", "confidence": 0.4848686754703522, "topleft": {"x": 14, "y": 90}, "bottomright": {"x": 25, "y": 102}}, {"label": "class", "confidence": 0.664940595626831, "topleft": {"x": 32, "y": 96}, "bottomright": {"x": 41, "y": 108}}, {"label": "class", "confidence": 0.6412393450737, "topleft": {"x": 85, "y": 96}, "bottomright": {"x": 96, "y": 108}}, {"label": "class", "confidence": 0.5580338835716248, "topleft": {"x": 109, "y": 92}, "bottomright": {"x": 120, "y": 103}}, {"label": "class", "confidence": 0.7796047329902649, "topleft": {"x": 146, "y": 92}, "bottomright": {"x": 158, "y": 107}}, {"label": "class", "confidence": 0.34013110399246216, "topleft": {"x": 152, "y": 95}, "bottomright": {"x": 165, "y": 108}}, {"label": "class", "confidence": 0.5819247961044312, "topleft": {"x": 175, "y": 97}, "bottomright": {"x": 186, "y": 109}}, {"label": "class", "confidence": 0.3991090655326843, "topleft": {"x": 57, "y": 101}, "bottomright": {"x": 67, "y": 113}}, {"label": "class", "confidence": 0.3244566321372986, "topleft": {"x": 96, "y": 106}, "bottomright": {"x": 107, "y": 118}}, {"label": "class", "confidence": 0.4708080291748047, "topleft": {"x": 153, "y": 105}, "bottomright": {"x": 166, "y": 117}}, {"label": "class", "confidence": 0.596770703792572, "topleft": {"x": 64, "y": 111}, "bottomright": {"x": 74, "y": 123}}, {"label": "class", "confidence": 0.6908746957778931, "topleft": {"x": 155, "y": 111}, "bottomright": {"x": 166, "y": 123}}, {"label": "class", "confidence": 0.6682485938072205, "topleft": {"x": 171, "y": 112}, "bottomright": {"x": 182, "y": 124}}, {"label": "class", "confidence": 0.559017539024353, "topleft": {"x": 7, "y": 124}, "bottomright": {"x": 18, "y": 137}}, {"label": "class", "confidence": 0.6465467810630798, "topleft": {"x": 109, "y": 135}, "bottomright": {"x": 120, "y": 147}}, {"label": "class", "confidence": 0.7024826407432556, "topleft": {"x": 7, "y": 149}, "bottomright": {"x": 16, "y": 162}}, {"label": "class", "confidence": 0.643130362033844, "topleft": {"x": 66, "y": 149}, "bottomright": {"x": 76, "y": 160}}, {"label": "class", "confidence": 0.6533662676811218, "topleft": {"x": 148, "y": 149}, "bottomright": {"x": 159, "y": 161}}, {"label": "class", "confidence": 0.461521178483963, "topleft": {"x": 165, "y": 144}, "bottomright": {"x": 176, "y": 156}}, {"label": "class", "confidence": 0.5098881125450134, "topleft": {"x": 89, "y": 153}, "bottomright": {"x": 101, "y": 164}}, {"label": "class", "confidence": 0.6434633135795593, "topleft": {"x": 174, "y": 154}, "bottomright": {"x": 186, "y": 168}}, {"label": "class", "confidence": 0.5867111682891846, "topleft": {"x": 130, "y": 170}, "bottomright": {"x": 140, "y": 183}}, {"label": "class", "confidence": 0.709308922290802, "topleft": {"x": 154, "y": 169}, "bottomright": {"x": 165, "y": 182}}, {"label": "class", "confidence": 0.6295623183250427, "topleft": {"x": 15, "y": 174}, "bottomright": {"x": 25, "y": 187}}, {"label": "class", "confidence": 0.4576520025730133, "topleft": {"x": 137, "y": 177}, "bottomright": {"x": 146, "y": 190}}, {"label": "class", "confidence": 0.6685108542442322, "topleft": {"x": 141, "y": 179}, "bottomright": {"x": 150, "y": 190}}, {"label": "class", "confidence": 0.6527940630912781, "topleft": {"x": 29, "y": 188}, "bottomright": {"x": 41, "y": 198}}, {"label": "class", "confidence": 0.6648549437522888, "topleft": {"x": 72, "y": 189}, "bottomright": {"x": 83, "y": 199}}]