[{"label": "class", "confidence": 0.42189115285873413, "topleft": {"x": 48, "y": 4}, "bottomright": {"x": 61, "y": 15}}, {"label": "class", "confidence": 0.7966017127037048, "topleft": {"x": 91, "y": 0}, "bottomright": {"x": 105, "y": 11}}, {"label": "class", "confidence": 0.35590097308158875, "topleft": {"x": 226, "y": 6}, "bottomright": {"x": 236, "y": 14}}, {"label": "class", "confidence": 0.690302848815918, "topleft": {"x": 13, "y": 16}, "bottomright": {"x": 30, "y": 36}}, {"label": "class", "confidence": 0.6257697343826294, "topleft": {"x": 20, "y": 19}, "bottomright": {"x": 35, "y": 34}}, {"label": "class", "confidence": 0.537278950214386, "topleft": {"x": 34, "y": 16}, "bottomright": {"x": 52, "y": 35}}, {"label": "class", "confidence": 0.47618505358695984, "topleft": {"x": 30, "y": 43}, "bottomright": {"x": 47, "y": 60}}, {"label": "class", "confidence": 0.5459069013595581, "topleft": {"x": 212, "y": 53}, "bottomright": {"x": 225, "y": 68}}, {"label": "class", "confidence": 0.594456672668457, "topleft": {"x": 1, "y": 75}, "bottomright": {"x": 9, "y": 95}}, {"label": "class", "confidence": 0.7127943634986877, "topleft": {"x": 82, "y": 96}, "bottomright": {"x": 96, "y": 113}}, {"label": "class", "confidence": 0.43999671936035156, "topleft": {"x": 193, "y": 98}, "bottomright": {"x": 206, "y": 113}}, {"label": "class", "confidence": 0.6482861638069153, "topleft": {"x": 0, "y": 127}, "bottomright": {"x": 2, "y": 141}}, {"label": "class", "confidence": 0.8446242213249207, "topleft": {"x": 1, "y": 125}, "bottomright": {"x": 6, "y": 141}}, {"label": "class", "confidence": 0.4802122712135315, "topleft": {"x": 0, "y": 126}, "bottomright": {"x": 1, "y": 139}}, {"label": "class", "confidence": 0.4962063431739807, "topleft": {"x": 17, "y": 125}, "bottomright": {"x": 35, "y": 140}}, {"label": "class", "confidence": 0.6250329613685608, "topleft": {"x": 34, "y": 127}, "bottomright": {"x": 51, "y": 140}}, {"label": "class", "confidence": 0.6384783387184143, "topleft": {"x": 43, "y": 123}, "bottomright": {"x": 64, "y": 142}}, {"label": "class", "confidence": 0.5135295391082764, "topleft": {"x": 82, "y": 125}, "bottomright": {"x": 100, "y": 139}}, {"label": "class", "confidence": 0.6408224105834961, "topleft": {"x": 90, "y": 121}, "bottomright": {"x": 106, "y": 138}}, {"label": "class", "confidence": 0.41442057490348816, "topleft": {"x": 144, "y": 127}, "bottomright": {"x": 159, "y": 140}}, {"label": "class", "confidence": 0.481988787651062, "topleft": {"x": 138, "y": 124}, "bottomright": {"x": 158, "y": 144}}, {"label": "class", "confidence": 0.3091256022453308, "topleft": {"x": 161, "y": 127}, "bottomright": {"x": 176, "y": 140}}, {"label": "class", "confidence": 0.3506722152233124, "topleft": {"x": 153, "y": 124}, "bottomright": {"x": 175, "y": 144}}, {"label": "class", "confidence": 0.656343400478363, "topleft": {"x": 178, "y": 127}, "bottomright": {"x": 194, "y": 142}}, {"label": "class", "confidence": 0.7336534857749939, "topleft": {"x": 185, "y": 124}, "bottomright": {"x": 202, "y": 143}}, {"label": "class", "confidence": 0.446503221988678, "topleft": {"x": 255, "y": 129}, "bottomright": {"x": 270, "y": 142}}, {"label": "class", "confidence": 0.5881519913673401, "topleft": {"x": 292, "y": 126}, "bottomright": {"x": 299, "y": 143}}, {"label": "class", "confidence": 0.40637120604515076, "topleft": {"x": 257, "y": 138}, "bottomright": {"x": 272, "y": 153}}, {"label": "class", "confidence": 0.6287283897399902, "topleft": {"x": 67, "y": 156}, "bottomright": {"x": 80, "y": 170}}, {"label": "class", "confidence": 0.6232596635818481, "topleft": {"x": 147, "y": 187}, "bottomright": {"x": 160, "y": 202}}, {"label": "class", "confidence": 0.600218653678894, "topleft": {"x": 153, "y": 184}, "bottomright": {"x": 172, "y": 206}}, {"label": "class", "confidence": 0.3926057517528534, "topleft": {"x": 257, "y": 194}, "bottomright": {"x": 271, "y": 209}}, {"label": "class", "confidence": 0.3330281674861908, "topleft": {"x": 99, "y": 204}, "bottomright": {"x": 111, "y": 220}}, {"label": "class", "confidence": 0.31027519702911377, "topleft": {"x": 91, "y": 201}, "bottomright": {"x": 109, "y": 223}}, {"label": "class", "confidence": 0.36882278323173523, "topleft": {"x": 285, "y": 234}, "bottomright": {"x": 297, "y": 248}}, {"label": "class", "confidence": 0.34133511781692505, "topleft": {"x": 292, "y": 233}, "bottomright": {"x": 299, "y": 252}}, {"label": "class", "confidence": 0.6604431867599487, "topleft": {"x": 145, "y": 251}, "bottomright": {"x": 160, "y": 269}}, {"label": "class", "confidence": 0.6879598498344421, "topleft": {"x": 35, "y": 270}, "bottomright": {"x": 49, "y": 289}}, {"label": "class", "confidence": 0.5252970457077026, "topleft": {"x": 91, "y": 269}, "bottomright": {"x": 103, "y": 286}}, {"label": "class", "confidence": 0.5377912521362305, "topleft": {"x": 175, "y": 270}, "bottomright": {"x": 192, "y": 289}}, {"label": "class", "confidence": 0.3554869294166565, "topleft": {"x": 90, "y": 280}, "bottomright": {"x": 103, "y": 295}}, {"label": "class", "confidence": 0.435748815536499, "topleft": {"x": 161, "y": 284}, "bottomright": {"x": 180, "y": 298}}, {"label": "class", "confidence": 0.3357379138469696, "topleft": {"x": 169, "y": 281}, "bottomright": {"x": 183, "y": 294}}]